{"name":"Agile-Diamond","tagline":"Project management framework for Flask-Diamond","body":"# Agile-Diamond\r\n\r\n**Agile-Diamond** contains everything needed to start and control an Agile software project.\r\n\r\n## Install python pre-requisites\r\n\r\n    pip install mr.bob\r\n\r\n## Clone the skeleton\r\n\r\n    git clone https://github.com/diamond-org/agile-diamond.git /tmp/agile-diamond\r\n\r\n## Scaffold the skeleton in the current directory\r\n\r\n    mkdir my-agile-project && cd my-agile-project\r\n    mrbob -w /tmp/agile-diamond/skel\r\n    less Readme.md\r\n\r\n## Test the skeleton\r\n\r\nIt is possible to test the skeleton in the local directory.  The following process will build everything.\r\n\r\n    make test\r\n\r\nAlso, test the graffle-rendering function\r\n\r\n    make test-graffle\r\n\r\n## Application Development with Flask-Diamond\r\n\r\nAgile-Diamond is well suited to application development using the [Flask-Diamond](http://flask-diamond.org) framework.  **Flask-Diamond** is a batteries-included Flask framework. Easily scaffold a working application with sensible defaults, then override the defaults to customize it for your goals.\r\n","google":"","note":"Don't delete this file! It's used internally to help with page regeneration."}